decentro_in_kyc_client/__init__.py
decentro_in_kyc_client/api_client.py
decentro_in_kyc_client/api_response.py
decentro_in_kyc_client/apis/__init__.py
decentro_in_kyc_client/apis/path_to_api.py
decentro_in_kyc_client/apis/paths/__init__.py
decentro_in_kyc_client/apis/paths/kyc_public_registry_validate.py
decentro_in_kyc_client/apis/paths/kyc_scan_extract_ocr.py
decentro_in_kyc_client/apis/paths/v2_kyc_document_classification.py
decentro_in_kyc_client/apis/paths/v2_kyc_forensics_face_match.py
decentro_in_kyc_client/apis/paths/v2_kyc_forensics_image_quality.py
decentro_in_kyc_client/apis/paths/v2_kyc_forensics_photocopy_check.py
decentro_in_kyc_client/apis/paths/v2_kyc_forensics_video_liveness.py
decentro_in_kyc_client/apis/paths/v2_kyc_identities_mask_aadhaar_uid.py
decentro_in_kyc_client/apis/tag_to_api.py
decentro_in_kyc_client/apis/tags/__init__.py
decentro_in_kyc_client/apis/tags/kyc_api.py
decentro_in_kyc_client/client.py
decentro_in_kyc_client/client.pyi
decentro_in_kyc_client/client_custom.py
decentro_in_kyc_client/configuration.py
decentro_in_kyc_client/exceptions.py
decentro_in_kyc_client/exceptions_base.py
decentro_in_kyc_client/model/__init__.py
decentro_in_kyc_client/model/check_image_quality400_response.py
decentro_in_kyc_client/model/check_image_quality400_response.pyi
decentro_in_kyc_client/model/check_image_quality_request.py
decentro_in_kyc_client/model/check_image_quality_request.pyi
decentro_in_kyc_client/model/check_image_quality_response.py
decentro_in_kyc_client/model/check_image_quality_response.pyi
decentro_in_kyc_client/model/check_photocopy400_response.py
decentro_in_kyc_client/model/check_photocopy400_response.pyi
decentro_in_kyc_client/model/check_photocopy_request.py
decentro_in_kyc_client/model/check_photocopy_request.pyi
decentro_in_kyc_client/model/check_photocopy_response.py
decentro_in_kyc_client/model/check_photocopy_response.pyi
decentro_in_kyc_client/model/check_video_liveness400_response.py
decentro_in_kyc_python_sdk-4.4.0.dist-info/LICENSE
decentro_in_kyc_python_sdk-4.4.0.dist-info/METADATA
decentro_in_kyc_python_sdk-4.4.0.dist-info/WHEEL
decentro_in_kyc_python_sdk-4.4.0.dist-info/RECORD
