Metadata-Version: 2.1
Name: decentro-in-kyc-python-sdk
Version: 4.4.0
Summary: KYC &amp; Onboarding
License: MIT
Author: Decentro
Author-email: admin@decentro.tech
Requires-Python: >=3.7,<4.0
Classifier: License :: OSI Approved :: MIT License
Classifier: Programming Language :: Python :: 3
Classifier: Programming Language :: Python :: 3.7
Classifier: Programming Language :: Python :: 3.8
Classifier: Programming Language :: Python :: 3.9
Classifier: Programming Language :: Python :: 3.10
Classifier: Programming Language :: Python :: 3.11
Requires-Dist: aiohttp (>=3.8.4,<4.0.0)
Requires-Dist: certifi (==2022.12.7)
Requires-Dist: frozendict (==2.3.4)
Requires-Dist: python-dateutil (==2.8.2)
Requires-Dist: typing_extensions (==4.3.0)
Requires-Dist: urllib3 (==1.26.7)
Requires-Dist: validators (==0.20.0)
